tsbootstrap/__init__.py
tsbootstrap/base_bootstrap.py
tsbootstrap/base_bootstrap_configs.py
tsbootstrap/block_bootstrap.py
tsbootstrap/block_bootstrap_configs.py
tsbootstrap/block_generator.py
tsbootstrap/block_length_sampler.py
tsbootstrap/block_resampler.py
tsbootstrap/bootstrap.py
tsbootstrap/markov_sampler.py
tsbootstrap/py.typed
tsbootstrap/ranklags.py
tsbootstrap/time_series_model.py
tsbootstrap/time_series_simulator.py
tsbootstrap/tsfit.py
tsbootstrap/registry/__init__.py
tsbootstrap/registry/_lookup.py
tsbootstrap/registry/_tags.py
tsbootstrap/registry/tests/__init__.py
tsbootstrap/registry/tests/test_tags.py
tsbootstrap/tests/__init__.py
tsbootstrap/tests/test_all_bootstraps.py
tsbootstrap/tests/test_all_estimators.py
tsbootstrap/tests/test_class_register.py
tsbootstrap/tests/test_switch.py
tsbootstrap/tests/scenarios/__init__.py
tsbootstrap/tests/scenarios/scenarios.py
tsbootstrap/tests/scenarios/scenarios_bootstrap.py
tsbootstrap/tests/scenarios/scenarios_getter.py
tsbootstrap/utils/__init__.py
tsbootstrap/utils/dependencies.py
tsbootstrap/utils/estimator_checks.py
tsbootstrap/utils/odds_and_ends.py
tsbootstrap/utils/types.py
tsbootstrap/utils/validate.py
tsbootstrap-0.1.5.dist-info/LICENSE
tsbootstrap-0.1.5.dist-info/METADATA
tsbootstrap-0.1.5.dist-info/WHEEL
tsbootstrap-0.1.5.dist-info/top_level.txt
tsbootstrap-0.1.5.dist-info/RECORD
