Metadata-Version: 2.1
Name: tsbootstrap
Version: 0.1.5
Summary: A Python package to generate bootstrapped time series
Author-email: Sankalp Gilda <sankalp.gilda@gmail.com>
Maintainer-email: Sankalp Gilda <sankalp.gilda@gmail.com>, Franz Kiraly <franz.kiraly@sktime.net>, Benedikt Heidrich <benedikt.heidrich@sktime.net>
License: MIT License
Classifier: Development Status :: 4 - Beta
Classifier: Intended Audience :: Science/Research
Classifier: Intended Audience :: Developers
Classifier: Operating System :: MacOS
Classifier: Operating System :: Microsoft :: Windows
Classifier: Operating System :: Unix
Classifier: Programming Language :: Python
Classifier: Programming Language :: Python :: 3 :: Only
Classifier: Programming Language :: Python :: 3.9
Classifier: Programming Language :: Python :: 3.10
Classifier: Programming Language :: Python :: 3.11
Classifier: Programming Language :: Python :: 3.12
Requires-Python: <3.13,>=3.9
License-File: LICENSE
Requires-Dist: numpy <1.27,>=1.21
Requires-Dist: scikit-base <0.11,>=0.10.0
Requires-Dist: scikit-learn <1.6.0,>=1.5.1
Requires-Dist: scipy <1.14.0,>=1.13
Requires-Dist: packaging <24.2,>=24.0
Requires-Dist: pydantic <3.0,>=2.0
Provides-Extra: all-extras
Requires-Dist: arch <7.1.0,>=7.0.0 ; extra == 'all-extras'
Requires-Dist: hmmlearn <0.3.2,>=0.3.0 ; extra == 'all-extras'
Requires-Dist: pyclustering <0.11.0,>=0.10.0 ; extra == 'all-extras'
Requires-Dist: scikit-learn-extra <0.4.0,>=0.3.0 ; extra == 'all-extras'
Requires-Dist: statsmodels <0.15.0,>=0.14.2 ; extra == 'all-extras'
Requires-Dist: dtaidistance ; (python_version < "3.10") and extra == 'all-extras'
Provides-Extra: dev
Requires-Dist: black >=24.3.0 ; extra == 'dev'
Requires-Dist: blacken-docs ; extra == 'dev'
Requires-Dist: hypothesis ; extra == 'dev'
Requires-Dist: pre-commit ; extra == 'dev'
Requires-Dist: pytest ; extra == 'dev'
Requires-Dist: pytest-cov ; extra == 'dev'
Requires-Dist: github-actions ; extra == 'dev'
Requires-Dist: importlib-metadata ; extra == 'dev'
Requires-Dist: pip-tools ; extra == 'dev'
Requires-Dist: pyright ; extra == 'dev'
Requires-Dist: ruff ; extra == 'dev'
Requires-Dist: autoflake ; extra == 'dev'
Requires-Dist: typos ; extra == 'dev'
Requires-Dist: tox ; extra == 'dev'
Requires-Dist: tox-gh-actions ; extra == 'dev'
Requires-Dist: pycobertura ; extra == 'dev'
Requires-Dist: tomlkit ; extra == 'dev'
Provides-Extra: docs
Requires-Dist: furo ; extra == 'docs'
Requires-Dist: jupyter ; extra == 'docs'
Requires-Dist: myst-parser ; extra == 'docs'
Requires-Dist: nbsphinx >=0.8.6 ; extra == 'docs'
Requires-Dist: numpydoc ; extra == 'docs'
Requires-Dist: pydata-sphinx-theme ; extra == 'docs'
Requires-Dist: Sphinx !=7.2.0,<8.0.0 ; extra == 'docs'
Requires-Dist: sphinx-rtd-theme >=1.3.0 ; extra == 'docs'
Requires-Dist: sphinx-copybutton >=0.5.2 ; extra == 'docs'
Requires-Dist: sphinx-design <0.6.0 ; extra == 'docs'
Requires-Dist: sphinx-gallery <0.15.0 ; extra == 'docs'
Requires-Dist: sphinx-issues <4.0.0 ; extra == 'docs'
Requires-Dist: sphinx-version-warning ; extra == 'docs'
Requires-Dist: tabulate >=0.9.0 ; extra == 'docs'
